<?xml version="1.0"?>
<!DOCTYPE dataset SYSTEM "data.dtd">
<dataset>
    <AP_PMT_RQST_ACCT_T ACCOUNT_NBR="2231461" ACLN_PCT="100"
        DISENC_AMT="0" FIN_COA_CD="BL" FIN_OBJECT_CD="7303"
        ITM_ACCT_TOT_AMT="300"
        OBJ_ID="5B1BF66B-C41D-EAC8-B741-DD26CD866C3D"
        PMT_RQST_ACCT_ID="1002" PMT_RQST_ITM_ID="1002" VER_NBR="5"/>
    <AP_PMT_RQST_ACCT_T ACCOUNT_NBR="2231461" ACLN_PCT="100"
        DISENC_AMT="0" FIN_COA_CD="BL" FIN_OBJECT_CD="7303"
        ITM_ACCT_TOT_AMT="349"
        OBJ_ID="CFC2EAEE-6F9A-AA71-20B5-0A42A4443DB1"
        PMT_RQST_ACCT_ID="1003" PMT_RQST_ITM_ID="1003" VER_NBR="5"/>
    <AP_PMT_RQST_ACCT_T ACCOUNT_NBR="2231461" ACLN_PCT="100"
        DISENC_AMT="0" FIN_COA_CD="BL" FIN_OBJECT_CD="7303"
        ITM_ACCT_TOT_AMT="141"
        OBJ_ID="22F557F3-5E52-954C-67F9-D1CBDDB4AE58"
        PMT_RQST_ACCT_ID="1004" PMT_RQST_ITM_ID="1004" VER_NBR="5"/>
    <AP_PMT_RQST_ACCT_T ACCOUNT_NBR="9323000" ACLN_PCT="100"
        DISENC_AMT="0" FIN_COA_CD="UA" FIN_OBJECT_CD="5081"
        ITM_ACCT_TOT_AMT="100"
        OBJ_ID="52A05BCB-395D-ED4E-6285-707911D892C5"
        PMT_RQST_ACCT_ID="1006" PMT_RQST_ITM_ID="1009" VER_NBR="5"/>
    <AP_PMT_RQST_ACCT_T ACCOUNT_NBR="9323000" ACLN_PCT="100"
        DISENC_AMT="0" FIN_COA_CD="UA" FIN_OBJECT_CD="5081"
        ITM_ACCT_TOT_AMT="100"
        OBJ_ID="A7C3D83C-C9AC-37EB-F338-2A17257D9838"
        PMT_RQST_ACCT_ID="1007" PMT_RQST_ITM_ID="1010" VER_NBR="5"/>
    <AP_PMT_RQST_ACCT_T ACCOUNT_NBR="9323000" ACLN_PCT="100"
        DISENC_AMT="0" FIN_COA_CD="UA" FIN_OBJECT_CD="5081"
        ITM_ACCT_TOT_AMT="100"
        OBJ_ID="D629D44F-6BE0-D03E-F595-CDD1CFBA16ED"
        PMT_RQST_ACCT_ID="1009" PMT_RQST_ITM_ID="1015" VER_NBR="5"/>
    <AP_PMT_RQST_ACCT_T ACCOUNT_NBR="9323000" ACLN_PCT="100"
        DISENC_AMT="0" FIN_COA_CD="UA" FIN_OBJECT_CD="5081"
        ITM_ACCT_TOT_AMT="100"
        OBJ_ID="17C0E903-B8BF-2145-4BB7-0A96DFE15651"
        PMT_RQST_ACCT_ID="1010" PMT_RQST_ITM_ID="1016" VER_NBR="5"/>
    <AP_PMT_RQST_ACCT_T ACCOUNT_NBR="9323000" ACLN_PCT="100"
        DISENC_AMT="0" FIN_COA_CD="UA" FIN_OBJECT_CD="5081"
        ITM_ACCT_TOT_AMT="0"
        OBJ_ID="F0291629-2C7C-C134-CD53-FBCF92763F05"
        PMT_RQST_ACCT_ID="1012" PMT_RQST_ITM_ID="1021" VER_NBR="1"/>
    <AP_PMT_RQST_ACCT_T ACCOUNT_NBR="9323000" ACLN_PCT="100"
        DISENC_AMT="0" FIN_COA_CD="UA" FIN_OBJECT_CD="5081"
        ITM_ACCT_TOT_AMT="0"
        OBJ_ID="C57D1B80-4072-19B0-DADC-A8FBE82182B8"
        PMT_RQST_ACCT_ID="1013" PMT_RQST_ITM_ID="1022" VER_NBR="1"/>
    <AP_PMT_RQST_ACCT_T ACCOUNT_NBR="9323000" ACLN_PCT="100"
        DISENC_AMT="0" FIN_COA_CD="UA" FIN_OBJECT_CD="5081"
        ITM_ACCT_TOT_AMT="100"
        OBJ_ID="5CFB7AF3-BE9C-4B73-9FE0-140CC00A9B86"
        PMT_RQST_ACCT_ID="1014" PMT_RQST_ITM_ID="1027" VER_NBR="5"/>
    <AP_PMT_RQST_ACCT_T ACCOUNT_NBR="1023200" ACLN_PCT="100"
        DISENC_AMT="0" FIN_COA_CD="BL" FIN_OBJECT_CD="4042"
        ITM_ACCT_TOT_AMT="150"
        OBJ_ID="5EB9597C-F448-F9A7-3B10-EE4FE6F08275"
        PMT_RQST_ACCT_ID="1020" PMT_RQST_ITM_ID="1039" VER_NBR="9"/>
    <AP_PMT_RQST_ACCT_T ACCOUNT_NBR="9323000" ACLN_PCT="100"
        DISENC_AMT="0" FIN_COA_CD="UA" FIN_OBJECT_CD="5081"
        ITM_ACCT_TOT_AMT="200"
        OBJ_ID="B9BFC926-6243-F795-D4A6-B494F6F07DDB"
        PMT_RQST_ACCT_ID="1017" PMT_RQST_ITM_ID="1033" VER_NBR="5"/>
    <AP_PMT_RQST_ACCT_T ACCOUNT_NBR="9323000" ACLN_PCT="100"
        DISENC_AMT="0" FIN_COA_CD="UA" FIN_OBJECT_CD="5081"
        ITM_ACCT_TOT_AMT="250"
        OBJ_ID="3B52E2F8-94D0-0961-7FC7-314E4B54E594"
        PMT_RQST_ACCT_ID="1024" PMT_RQST_ITM_ID="1046" VER_NBR="5"/>
</dataset>
