<?xml version="1.0"?>
<!DOCTYPE dataset SYSTEM "data.dtd">
<dataset>
    <CA_UBO_FUNC_T FIN_UBO_FUNC_CD="AA"
        FIN_UBO_FUNC_NM="ACADEMIC ADMINISTRATION"
        OBJ_ID="0DF11C6DE70138F2E043814FD88138F2" VER_NBR="1"/>
    <CA_UBO_FUNC_T FIN_UBO_FUNC_CD="AC"
        FIN_UBO_FUNC_NM="ACADEMIC COMPUTING"
        OBJ_ID="0DF11C6DE70238F2E043814FD88138F2" VER_NBR="1"/>
    <CA_UBO_FUNC_T FIN_UBO_FUNC_CD="AD"
        FIN_UBO_FUNC_NM="ACADEMIC DEVELOPMENT"
        OBJ_ID="0DF11C6DE70338F2E043814FD88138F2" VER_NBR="1"/>
    <CA_UBO_FUNC_T FIN_UBO_FUNC_CD="AUX"
        FIN_UBO_FUNC_NM="AUXILIARY &amp; SERVICES"
        OBJ_ID="0DF11C6DE70438F2E043814FD88138F2" VER_NBR="1"/>
    <CA_UBO_FUNC_T FIN_UBO_FUNC_CD="AVS"
        FIN_UBO_FUNC_NM="AUDIO VISUAL SERVICES"
        OBJ_ID="0DF11C6DE70538F2E043814FD88138F2" VER_NBR="1"/>
    <CA_UBO_FUNC_T FIN_UBO_FUNC_CD="CS"
        FIN_UBO_FUNC_NM="COMMUNITY SERVICES"
        OBJ_ID="0DF11C6DE70638F2E043814FD88138F2" VER_NBR="1"/>
    <CA_UBO_FUNC_T FIN_UBO_FUNC_CD="IN" FIN_UBO_FUNC_NM="INSTRUCTION"
        OBJ_ID="0DF11C6DE70738F2E043814FD88138F2" VER_NBR="1"/>
    <CA_UBO_FUNC_T FIN_UBO_FUNC_CD="IPR"
        FIN_UBO_FUNC_NM="INDIVIDUAL OR PROJECT RESEARCH"
        OBJ_ID="0DF11C6DE70838F2E043814FD88138F2" VER_NBR="1"/>
    <CA_UBO_FUNC_T FIN_UBO_FUNC_CD="IRC"
        FIN_UBO_FUNC_NM="INSTITUTES AND RESEARCH CENTERS"
        OBJ_ID="0DF11C6DE70938F2E043814FD88138F2" VER_NBR="1"/>
    <CA_UBO_FUNC_T FIN_UBO_FUNC_CD="IS"
        FIN_UBO_FUNC_NM="INSTITUTIONAL SUPPORT"
        OBJ_ID="0DF11C6DE70A38F2E043814FD88138F2" VER_NBR="1"/>
    <CA_UBO_FUNC_T FIN_UBO_FUNC_CD="LIB" FIN_UBO_FUNC_NM="LIBRARIES"
        OBJ_ID="0DF11C6DE70B38F2E043814FD88138F2" VER_NBR="1"/>
    <CA_UBO_FUNC_T FIN_UBO_FUNC_CD="M&amp;G"
        FIN_UBO_FUNC_NM="MUSEUMS AND GALLERIES"
        OBJ_ID="0DF11C6DE70C38F2E043814FD88138F2" VER_NBR="1"/>
    <CA_UBO_FUNC_T FIN_UBO_FUNC_CD="NA"
        FIN_UBO_FUNC_NM="NOT APPLICABLE TO ACCOUNT"
        OBJ_ID="0DF11C6DE70D38F2E043814FD88138F2" VER_NBR="1"/>
    <CA_UBO_FUNC_T FIN_UBO_FUNC_CD="PBS"
        FIN_UBO_FUNC_NM="PUBLIC BROADCASTING SERVICES"
        OBJ_ID="0DF11C6DE70E38F2E043814FD88138F2" VER_NBR="1"/>
    <CA_UBO_FUNC_T FIN_UBO_FUNC_CD="PP" FIN_UBO_FUNC_NM="PHYSICAL PLANT"
        OBJ_ID="0DF11C6DE70F38F2E043814FD88138F2" VER_NBR="1"/>
    <CA_UBO_FUNC_T FIN_UBO_FUNC_CD="PRD"
        FIN_UBO_FUNC_NM="PUBLIC RELATIONS AND DEVELOPMENT"
        OBJ_ID="0DF11C6DE71038F2E043814FD88138F2" VER_NBR="1"/>
    <CA_UBO_FUNC_T FIN_UBO_FUNC_CD="PS"
        FIN_UBO_FUNC_NM="PATIENT SERVICES"
        OBJ_ID="0DF11C6DE71138F2E043814FD88138F2" VER_NBR="1"/>
    <CA_UBO_FUNC_T FIN_UBO_FUNC_CD="S&amp;F"
        FIN_UBO_FUNC_NM="SCHOLARSHIPS &amp; FELLOWSHIPS"
        OBJ_ID="0DF11C6DE71238F2E043814FD88138F2" VER_NBR="1"/>
    <CA_UBO_FUNC_T FIN_UBO_FUNC_CD="SCD"
        FIN_UBO_FUNC_NM="SOCIAL AND CULTURAL DEVELOPMENT"
        OBJ_ID="0DF11C6DE71338F2E043814FD88138F2" VER_NBR="1"/>
    <CA_UBO_FUNC_T FIN_UBO_FUNC_CD="SPA"
        FIN_UBO_FUNC_NM="SPONSORED PROGRAM AD."
        OBJ_ID="0DF11C6DE71438F2E043814FD88138F2" VER_NBR="1"/>
    <CA_UBO_FUNC_T FIN_UBO_FUNC_CD="SRA"
        FIN_UBO_FUNC_NM="STUDENT RECRUITMENT ADMISSIONS &amp; RECORDS"
        OBJ_ID="0DF11C6DE71538F2E043814FD88138F2" VER_NBR="1"/>
    <CA_UBO_FUNC_T FIN_UBO_FUNC_CD="SS"
        FIN_UBO_FUNC_NM="STUDENT SERVICES"
        OBJ_ID="0DF11C6DE71638F2E043814FD88138F2" VER_NBR="1"/>
</dataset>
