<?xml version="1.0"?>
<!DOCTYPE dataset SYSTEM "data.dtd">
<dataset>
    <EN_RTE_BRCH_ST_T DB_LOCK_VER_NBR="2" RTE_BRCH_ID="563357421"
        RTE_BRCH_ST_ID="563357428"
        ST_KEY="System.PostProcessorProcessed" ST_VAL_TXT="true"/>
    <EN_RTE_BRCH_ST_T DB_LOCK_VER_NBR="1" RTE_BRCH_ID="563357421"
        RTE_BRCH_ST_ID="563357429" ST_KEY="System.PostProcessorFinal" ST_VAL_TXT="true"/>
    <EN_RTE_BRCH_ST_T DB_LOCK_VER_NBR="2" RTE_BRCH_ID="563357430"
        RTE_BRCH_ST_ID="563357432"
        ST_KEY="System.PostProcessorProcessed" ST_VAL_TXT="true"/>
    <EN_RTE_BRCH_ST_T DB_LOCK_VER_NBR="1" RTE_BRCH_ID="563357430"
        RTE_BRCH_ST_ID="563357435" ST_KEY="System.PostProcessorFinal" ST_VAL_TXT="true"/>
    <EN_RTE_BRCH_ST_T DB_LOCK_VER_NBR="2" RTE_BRCH_ID="563357469"
        RTE_BRCH_ST_ID="563357472"
        ST_KEY="System.PostProcessorProcessed" ST_VAL_TXT="true"/>
    <EN_RTE_BRCH_ST_T DB_LOCK_VER_NBR="1" RTE_BRCH_ID="563357469"
        RTE_BRCH_ST_ID="563357473" ST_KEY="System.PostProcessorFinal" ST_VAL_TXT="true"/>
    <EN_RTE_BRCH_ST_T DB_LOCK_VER_NBR="2" RTE_BRCH_ID="563357474"
        RTE_BRCH_ST_ID="563357477"
        ST_KEY="System.PostProcessorProcessed" ST_VAL_TXT="true"/>
    <EN_RTE_BRCH_ST_T DB_LOCK_VER_NBR="1" RTE_BRCH_ID="563357474"
        RTE_BRCH_ST_ID="563357478" ST_KEY="System.PostProcessorFinal" ST_VAL_TXT="true"/>
    <EN_RTE_BRCH_ST_T DB_LOCK_VER_NBR="2" RTE_BRCH_ID="563357739"
        RTE_BRCH_ST_ID="563357742"
        ST_KEY="System.PostProcessorProcessed" ST_VAL_TXT="true"/>
    <EN_RTE_BRCH_ST_T DB_LOCK_VER_NBR="1" RTE_BRCH_ID="563357739"
        RTE_BRCH_ST_ID="563357743" ST_KEY="System.PostProcessorFinal" ST_VAL_TXT="true"/>
    <EN_RTE_BRCH_ST_T DB_LOCK_VER_NBR="2" RTE_BRCH_ID="563357749"
        RTE_BRCH_ST_ID="563357752"
        ST_KEY="System.PostProcessorProcessed" ST_VAL_TXT="true"/>
    <EN_RTE_BRCH_ST_T DB_LOCK_VER_NBR="1" RTE_BRCH_ID="563357749"
        RTE_BRCH_ST_ID="563357753" ST_KEY="System.PostProcessorFinal" ST_VAL_TXT="true"/>
</dataset>
