<?xml version="1.0"?>
<!DOCTYPE dataset SYSTEM "data.dtd">
<dataset>
    <LD_A21_RPT_POS_T A21_LBR_RPT_NBR="A02" LBR_RPT_POSOBJ_CD="AC"
        OBJ_ID="433ADA6D39BE90E8E043814FD88190E8" ROW_ACTV_IND="Y"
        UNIV_FISCAL_YR="2007" VER_NBR="1"/>
    <LD_A21_RPT_POS_T A21_LBR_RPT_NBR="M01" LBR_RPT_POSOBJ_CD="AC"
        OBJ_ID="433ADA6D39C090E8E043814FD88190E8" ROW_ACTV_IND="Y"
        UNIV_FISCAL_YR="2007" VER_NBR="1"/>
    <LD_A21_RPT_POS_T A21_LBR_RPT_NBR="M01" LBR_RPT_POSOBJ_CD="PA"
        OBJ_ID="433ADA6D39C190E8E043814FD88190E8" ROW_ACTV_IND="Y"
        UNIV_FISCAL_YR="2007" VER_NBR="1"/>
    <LD_A21_RPT_POS_T A21_LBR_RPT_NBR="M02" LBR_RPT_POSOBJ_CD="AC"
        OBJ_ID="433ADA6D39C290E8E043814FD88190E8" ROW_ACTV_IND="Y"
        UNIV_FISCAL_YR="2007" VER_NBR="1"/>
    <LD_A21_RPT_POS_T A21_LBR_RPT_NBR="M02" LBR_RPT_POSOBJ_CD="PA"
        OBJ_ID="433ADA6D39C390E8E043814FD88190E8" ROW_ACTV_IND="Y"
        UNIV_FISCAL_YR="2007" VER_NBR="1"/>
    <LD_A21_RPT_POS_T A21_LBR_RPT_NBR="B01" LBR_RPT_POSOBJ_CD="CL"
        OBJ_ID="433ADA6D39C490E8E043814FD88190E8" ROW_ACTV_IND="Y"
        UNIV_FISCAL_YR="2007" VER_NBR="1"/>
    <LD_A21_RPT_POS_T A21_LBR_RPT_NBR="B01" LBR_RPT_POSOBJ_CD="HO"
        OBJ_ID="433ADA6D39C590E8E043814FD88190E8" ROW_ACTV_IND="Y"
        UNIV_FISCAL_YR="2007" VER_NBR="1"/>
    <LD_A21_RPT_POS_T A21_LBR_RPT_NBR="B02" LBR_RPT_POSOBJ_CD="CL"
        OBJ_ID="433ADA6D39C690E8E043814FD88190E8" ROW_ACTV_IND="Y"
        UNIV_FISCAL_YR="2007" VER_NBR="1"/>
    <LD_A21_RPT_POS_T A21_LBR_RPT_NBR="B02" LBR_RPT_POSOBJ_CD="HO"
        OBJ_ID="433ADA6D39C790E8E043814FD88190E8" ROW_ACTV_IND="Y"
        UNIV_FISCAL_YR="2007" VER_NBR="1"/>
    <LD_A21_RPT_POS_T A21_LBR_RPT_NBR="B03" LBR_RPT_POSOBJ_CD="CL"
        OBJ_ID="433ADA6D39C890E8E043814FD88190E8" ROW_ACTV_IND="Y"
        UNIV_FISCAL_YR="2007" VER_NBR="1"/>
    <LD_A21_RPT_POS_T A21_LBR_RPT_NBR="B03" LBR_RPT_POSOBJ_CD="HO"
        OBJ_ID="433ADA6D39C990E8E043814FD88190E8" ROW_ACTV_IND="Y"
        UNIV_FISCAL_YR="2007" VER_NBR="1"/>
    <LD_A21_RPT_POS_T A21_LBR_RPT_NBR="B04" LBR_RPT_POSOBJ_CD="CL"
        OBJ_ID="433ADA6D39CA90E8E043814FD88190E8" ROW_ACTV_IND="Y"
        UNIV_FISCAL_YR="2007" VER_NBR="1"/>
    <LD_A21_RPT_POS_T A21_LBR_RPT_NBR="B04" LBR_RPT_POSOBJ_CD="HO"
        OBJ_ID="433ADA6D39CB90E8E043814FD88190E8" ROW_ACTV_IND="Y"
        UNIV_FISCAL_YR="2007" VER_NBR="1"/>
    <LD_A21_RPT_POS_T A21_LBR_RPT_NBR="S01" LBR_RPT_POSOBJ_CD="SU"
        OBJ_ID="433ADA6D39CC90E8E043814FD88190E8" ROW_ACTV_IND="Y"
        UNIV_FISCAL_YR="2007" VER_NBR="1"/>
</dataset>
