<?xml version="1.0"?>
<!DOCTYPE dataset SYSTEM "data.dtd">
<dataset>
    <PUR_AP_ITM_TYP_T DOBJ_MAINT_CD_ACTV_IND="Y" ITM_TYP_CD="FDTX"
        ITM_TYP_DESC="FEDERAL TAX" ITYP_ABV_THE_LN_IND="N"
        OBJ_ID="3F1E1EBA-AC7D-72D8-2532-5705C399D8E0" QTY_BSD_GL_IND="N" VER_NBR="3"/>
    <PUR_AP_ITM_TYP_T DOBJ_MAINT_CD_ACTV_IND="Y" ITM_TYP_CD="FDGR"
        ITM_TYP_DESC="FEDERAL TAX GROSS-UP" ITYP_ABV_THE_LN_IND="N"
        OBJ_ID="9A040B34-B954-0ABC-DF59-6521DEB0919C" QTY_BSD_GL_IND="N" VER_NBR="1"/>
    <PUR_AP_ITM_TYP_T DOBJ_MAINT_CD_ACTV_IND="Y" ITM_TYP_CD="FRHT"
        ITM_TYP_DESC="FREIGHT" ITYP_ABV_THE_LN_IND="N"
        OBJ_ID="F9DCA11A-CD24-F961-EE26-12B1C31D0360" QTY_BSD_GL_IND="N" VER_NBR="1"/>
    <PUR_AP_ITM_TYP_T DOBJ_MAINT_CD_ACTV_IND="Y" ITM_TYP_CD="ORDS"
        ITM_TYP_DESC="FULL ORDER DISCOUNT" ITYP_ABV_THE_LN_IND="N"
        OBJ_ID="BF44B7E5-D9E2-215A-55BE-7619F9614426" QTY_BSD_GL_IND="N" VER_NBR="1"/>
    <PUR_AP_ITM_TYP_T DOBJ_MAINT_CD_ACTV_IND="Y" ITM_TYP_CD="ITEM"
        ITM_TYP_DESC="QUANTITY" ITYP_ABV_THE_LN_IND="Y"
        OBJ_ID="F7C44E14-1128-60C6-71BA-151F4E113733" QTY_BSD_GL_IND="Y" VER_NBR="2"/>
    <PUR_AP_ITM_TYP_T DOBJ_MAINT_CD_ACTV_IND="Y" ITM_TYP_CD="RSTO"
        ITM_TYP_DESC="LESS RESTOCKING FEE" ITYP_ABV_THE_LN_IND="N"
        OBJ_ID="745F4C4C-08C4-B568-0206-CD6AA34C8D96" QTY_BSD_GL_IND="N" VER_NBR="1"/>
    <PUR_AP_ITM_TYP_T DOBJ_MAINT_CD_ACTV_IND="Y" ITM_TYP_CD="MNOR"
        ITM_TYP_DESC="MINIMUM ORDER" ITYP_ABV_THE_LN_IND="N"
        OBJ_ID="4145ED99-905A-9CD0-202F-44F79B34BF9B" QTY_BSD_GL_IND="N" VER_NBR="1"/>
    <PUR_AP_ITM_TYP_T DOBJ_MAINT_CD_ACTV_IND="Y" ITM_TYP_CD="MISC"
        ITM_TYP_DESC="MISCELLANEOUS" ITYP_ABV_THE_LN_IND="N"
        OBJ_ID="4511536F-C4FE-7C47-D3D9-3CD2D755C920" QTY_BSD_GL_IND="N" VER_NBR="1"/>
    <PUR_AP_ITM_TYP_T DOBJ_MAINT_CD_ACTV_IND="Y" ITM_TYP_CD="MSCR"
        ITM_TYP_DESC="MISCELLANEOUS CREDIT" ITYP_ABV_THE_LN_IND="N"
        OBJ_ID="26BF335C-A987-6244-0262-84E6C2DCEF03" QTY_BSD_GL_IND="N" VER_NBR="1"/>
    <PUR_AP_ITM_TYP_T DOBJ_MAINT_CD_ACTV_IND="Y" ITM_TYP_CD="DISC"
        ITM_TYP_DESC="PAYMENT TERMS DISCOUNT" ITYP_ABV_THE_LN_IND="N"
        OBJ_ID="2140BCA5-2D8D-F8EE-F29A-5231DE6EFFB7" QTY_BSD_GL_IND="N" VER_NBR="1"/>
    <PUR_AP_ITM_TYP_T DOBJ_MAINT_CD_ACTV_IND="Y" ITM_TYP_CD="SPHD"
        ITM_TYP_DESC="SHIPPING AND HANDLING" ITYP_ABV_THE_LN_IND="N"
        OBJ_ID="15BD285E-34F7-5AF4-5B73-0E99840CE750" QTY_BSD_GL_IND="N" VER_NBR="1"/>
    <PUR_AP_ITM_TYP_T DOBJ_MAINT_CD_ACTV_IND="Y" ITM_TYP_CD="STTX"
        ITM_TYP_DESC="STATE TAX" ITYP_ABV_THE_LN_IND="N"
        OBJ_ID="F026215A-B174-7418-34E3-A742B5EFEB0B" QTY_BSD_GL_IND="N" VER_NBR="1"/>
    <PUR_AP_ITM_TYP_T DOBJ_MAINT_CD_ACTV_IND="Y" ITM_TYP_CD="STGR"
        ITM_TYP_DESC="STATE TAX GROSS-UP" ITYP_ABV_THE_LN_IND="N"
        OBJ_ID="4F1A90CC-6FA0-DBD9-4AF7-396FB41A1499" QTY_BSD_GL_IND="N" VER_NBR="1"/>
    <PUR_AP_ITM_TYP_T DOBJ_MAINT_CD_ACTV_IND="Y" ITM_TYP_CD="TRDI"
        ITM_TYP_DESC="TRADE IN" ITYP_ABV_THE_LN_IND="N"
        OBJ_ID="6C5EE90A-AAAF-701A-CFBB-B3CADBC62506" QTY_BSD_GL_IND="N" VER_NBR="1"/>
    <PUR_AP_ITM_TYP_T DOBJ_MAINT_CD_ACTV_IND="Y" ITM_TYP_CD="SRVC"
        ITM_TYP_DESC="NO QUANTITY" ITYP_ABV_THE_LN_IND="Y"
        OBJ_ID="247F9EB07E9C6134E043814FD8816134" QTY_BSD_GL_IND="N" VER_NBR="1"/>
</dataset>
